certbot_dns_cloudxns/__init__.py
certbot_dns_cloudxns/py.typed
certbot_dns_cloudxns/_internal/__init__.py
certbot_dns_cloudxns/_internal/dns_cloudxns.py
certbot_dns_cloudxns-1.32.0.dist-info/LICENSE.txt
certbot_dns_cloudxns-1.32.0.dist-info/METADATA
certbot_dns_cloudxns-1.32.0.dist-info/WHEEL
certbot_dns_cloudxns-1.32.0.dist-info/entry_points.txt
certbot_dns_cloudxns-1.32.0.dist-info/top_level.txt
certbot_dns_cloudxns-1.32.0.dist-info/RECORD
