Metadata-Version: 2.1
Name: certbot-dns-cloudxns
Version: 1.32.0
Summary: CloudXNS DNS Authenticator plugin for Certbot
Home-page: https://github.com/certbot/certbot
Author: Certbot Project
Author-email: certbot-dev@eff.org
License: Apache License 2.0
Classifier: Development Status :: 5 - Production/Stable
Classifier: Environment :: Plugins
Classifier: Intended Audience :: System Administrators
Classifier: License :: OSI Approved :: Apache Software License
Classifier: Operating System :: POSIX :: Linux
Classifier: Programming Language :: Python
Classifier: Programming Language :: Python :: 3
Classifier: Programming Language :: Python :: 3.7
Classifier: Programming Language :: Python :: 3.8
Classifier: Programming Language :: Python :: 3.9
Classifier: Programming Language :: Python :: 3.10
Classifier: Topic :: Internet :: WWW/HTTP
Classifier: Topic :: Security
Classifier: Topic :: System :: Installation/Setup
Classifier: Topic :: System :: Networking
Classifier: Topic :: System :: Systems Administration
Classifier: Topic :: Utilities
Requires-Python: >=3.7
License-File: LICENSE.txt
Requires-Dist: dns-lexicon (>=3.2.1)
Requires-Dist: setuptools (>=41.6.0)
Requires-Dist: acme (>=1.32.0)
Requires-Dist: certbot (>=1.32.0)
Provides-Extra: docs
Requires-Dist: Sphinx (>=1.0) ; extra == 'docs'
Requires-Dist: sphinx-rtd-theme ; extra == 'docs'
